norming/__init__.py
norming/_utils.py
norming/core/__init__.py
norming/tests/__init__.py
norming/tests/test_tuple_0.py
norming/tests/test_tuple_qual.py
norming-0.1.0.dist-info/licenses/LICENSE.txt
norming-0.1.0.dist-info/METADATA
norming-0.1.0.dist-info/WHEEL
norming-0.1.0.dist-info/top_level.txt
norming-0.1.0.dist-info/RECORD
